{
  "type": "Feature",
  "properties": {
    "millsfield:wayfinding_detail": "ATR",
    "millsfield:wayfinding_kind": "T2",
    "sfo:level": 3,
    "sfomuseum:placetype": "waypoint",
    "sfomuseum:post_security": -1,
    "wof:adjencies": [
      1796889539,
      1796982269
    ],
    "wof:name": "AirTrain Terminal 2 Blue Line",
    "wof:placetype": "venue",
    "wof:placetype_alt": "waypoint"
  },
  "geometry": {"coordinates":[-122.3845219551329,37.616796550535916],"type":"Point"}
}
