{
  "type": "Feature",
  "properties": {
    "millsfield:wayfinding_detail": "T2",
    "millsfield:wayfinding_kind": "ATR",
    "sfo:level": 3,
    "sfomuseum:placetype": "waypoint",
    "sfomuseum:post_security": -1,
    "wof:adjencies": [
      1796889539,
      1796982269
    ],
    "wof:name": "AirTrain Terminal 2 Blue Line",
    "wof:placetype": "venue",
    "wof:placetype_alt": "waypoint"
  },
  "geometry": {"coordinates":[-122.38457325338547,37.616754066487616],"type":"Point"}
}
