{
  "type": "Feature",
  "properties": {
    "sfo:level": 3,
    "sfomuseum:placetype": "waypoint",
    "sfomuseum:post_security": 0,
    "wof:adjencies": [
      1796903587,
      1796889617
    ],
    "wof:name": "T3 - ITB Pre Security Connector ITB",
    "wof:placetype": "venue",
    "wof:placetype_alt": "waypoint"
  },
  "geometry": {"coordinates":[-122.38892390483936,37.61677926120961],"type":"Point"}
}
