{
  "type": "Feature",
  "properties": {
    "sfo:level": 2,
    "sfomuseum:placetype": "waypoint",
    "wof:name": "T3 - ITB Pre Security Connector ITB",
    "wof:placetype": "custom",
    "wof:placetype_alt": "waypoint"
  },
  "geometry": {"coordinates":[-122.38892390483936,37.61677926120961],"type":"Point"}
}
