{
  "type": "Feature",
  "properties": {
    "date:inception_lower": "2024-11-05",
    "date:inception_upper": "2024-11-05",
    "millsfield:wayfinding_detail": "D",
    "millsfield:wayfinding_kind": "T2",
    "sfo:level": 2,
    "sfomuseum:placetype": "waypoint",
    "sfomuseum:post_security": 1,
    "wof:adjacencies": [
      1914666233,
      1914666317,
      1914666683
    ],
    "wof:label": "T2 - T3 Post-Security Connector (T2) (2024-11-05)",
    "wof:name": "T2 - T3 Post-Security Connector (T2)",
    "wof:placetype": "venue",
    "wof:placetype_alt": [
      "waypoint"
    ]
  },
  "geometry": {"coordinates":[-122.38312631652008,37.61733495355036],"type":"Point"}
}
