{
  "type": "Feature",
  "properties": {
    "date:inception_lower": "2024-06-17",
    "date:inception_upper": "2024-06-17",
    "millsfield:wayfinding_detail": "ARR",
    "millsfield:wayfinding_kind": "T3",
    "sfo:level": 1,
    "sfomuseum:placetype": "waypoint",
    "sfomuseum:post_security": 0,
    "wof:adjencies": [
      1797018139,
      1797018141
    ],
    "wof:label": "Terminal 3 Arrivals / Baggage Claim Stairs Level 1 (2024-06-17)",
    "wof:name": "Terminal 3 Arrivals / Baggage Claim Stairs Level 1",
    "wof:placetype": "venue",
    "wof:placetype_alt": [
      "waypoint"
    ]
  },
  "geometry": {"coordinates":[-122.38692030460633,37.61822506200589],"type":"Point"}
}
