{
  "type": "Feature",
  "properties": {
    "date:inception_lower": "2024-06-17",
    "date:inception_upper": "2024-06-17",
    "millsfield:wayfinding_detail": "T3",
    "millsfield:wayfinding_kind": "ATR",
    "sfo:level": 0,
    "sfomuseum:placetype": "waypoint",
    "sfomuseum:post_security": -1,
    "wof:adjacencies": [
      1914666287,
      1914666283,
      1914666413
    ],
    "wof:label": "AirTrain Terminal 3 Station (2024-06-17)",
    "wof:name": "AirTrain Terminal 3 Station",
    "wof:placetype": "venue",
    "wof:placetype_alt": [
      "waypoint"
    ]
  },
  "geometry": {"coordinates":[-122.38660350961372,37.61752445584399],"type":"Point"}
}
