{
  "type": "Feature",
  "properties": {
    "date:inception_lower": "2024-06-17",
    "date:inception_upper": "2024-06-17",
    "millsfield:wayfinding_detail": "RCC",
    "millsfield:wayfinding_kind": "ATR",
    "sfo:level": 3,
    "sfomuseum:placetype": "waypoint",
    "sfomuseum:post_security": 0,
    "wof:adjacencies": [
      1914666571,
      1930431139
    ],
    "wof:label": "AirTrain Rental Car Center Blue Line (Outbound) (2024-06-17)",
    "wof:name": "AirTrain Rental Car Center Blue Line (Outbound)",
    "wof:placetype": "venue",
    "wof:placetype_alt": [
      "waypoint"
    ]
  },
  "geometry": {"coordinates":[-122.40116888909837,37.628154234836764],"type":"Point"}
}
