{
  "type": "Feature",
  "properties": {
    "date:inception_lower": "2024-11-05",
    "date:inception_upper": "2024-11-05",
    "millsfield:wayfinding_detail": "D",
    "millsfield:wayfinding_kind": "T2",
    "sfo:level": 2,
    "sfomuseum:placetype": "waypoint",
    "sfomuseum:post_security": 1,
    "wof:adjacencies": [
      1947305405,
      1947304843
    ],
    "wof:label": "T1 - T2 Post-Security Connector (T2) (2024-11-05)",
    "wof:name": "T1 - T2 Post-Security Connector (T2)",
    "wof:placetype": "venue",
    "wof:placetype_alt": [
      "waypoint"
    ]
  },
  "geometry": {"coordinates":[-122.382928,37.616828],"type":"Point"}
}
