{
  "type": "Feature",
  "properties": {
    "millsfield:wayfinding_detail": "C",
    "millsfield:wayfinding_kind": "T1",
    "sfo:level": 2,
    "sfomuseum:placetype": "waypoint",
    "sfomuseum:post_security": 1,
    "wof:adjencies": [
      1796889567
    ],
    "wof:name": "Gate C6 Waiting Area",
    "wof:placetype": "venue",
    "wof:placetype_alt": "waypoint"
  },
  "geometry": {"coordinates":[-122.38269795188522,37.61478834265107],"type":"Point"}
}
