{
  "type": "Feature",
  "properties": {
    "sfomuseum:placetype": "waypoint",
    "wof:name": "Gate C6 Waiting Area",
    "wof:placetype": "venue",
    "wof:placetype_alt": "waypoint"
  },
  "geometry": {"coordinates":[-122.38269795188522,37.61478834265107],"type":"Point"}
}
