{
  "type": "Feature",
  "properties": {
    "date:inception_lower": "2024-11-05",
    "date:inception_upper": "2024-11-05",
    "millsfield:wayfinding_detail": "T2",
    "millsfield:wayfinding_kind": "ATR",
    "sfo:level": 3,
    "sfomuseum:placetype": "waypoint",
    "sfomuseum:post_security": 0,
    "wof:adjacencies": [
      1914666775,
      1914666627,
      1914666629,
      1914666641
    ],
    "wof:label": "AirTrain Terminal 2 Stairs East Level 3 (2024-11-05)",
    "wof:name": "AirTrain Terminal 2 Stairs East Level 3",
    "wof:placetype": "venue",
    "wof:placetype_alt": [
      "waypoint"
    ]
  },
  "geometry": {"coordinates":[-122.38380057615976,37.616858759427494],"type":"Point"}
}
