{
  "type": "Feature",
  "properties": {
    "date:inception_lower": "2024-11-05",
    "date:inception_upper": "2024-11-05",
    "millsfield:wayfinding_detail": "DEP",
    "millsfield:wayfinding_kind": "T2",
    "sfo:level": 1,
    "sfomuseum:placetype": "waypoint",
    "sfomuseum:post_security": 0,
    "wof:adjacencies": [
      1947305455,
      1947304923,
      1947304983
    ],
    "wof:label": "Terminal 2 Main Hall West (2024-11-05)",
    "wof:name": "Terminal 2 Main Hall West",
    "wof:placetype": "venue",
    "wof:placetype_alt": [
      "waypoint"
    ]
  },
  "geometry": {"coordinates":[-122.38391709722474,37.61735035020315],"type":"Point"}
}
