{
  "type": "Feature",
  "properties": {
    "date:inception_lower": "2024-06-17",
    "date:inception_upper": "2024-06-17",
    "millsfield:wayfinding_detail": "C",
    "millsfield:wayfinding_kind": "T1",
    "sfo:level": 2,
    "sfomuseum:placetype": "waypoint",
    "sfomuseum:post_security": 1,
    "wof:adjacenies": [
      1914666323,
      1914666625,
      1914666637,
      1914666643,
      1914666639,
      1914666631
    ],
    "wof:adjencies": [
      1796889567,
      1796935553,
      1796935555,
      1796935559,
      1796935557,
      1796935551
    ],
    "wof:label": "Boarding Area C End Pier (2024-06-17)",
    "wof:name": "Boarding Area C End Pier",
    "wof:placetype": "venue",
    "wof:placetype_alt": [
      "waypoint"
    ]
  },
  "geometry": {"coordinates":[-122.38246357718941,37.61482921799332],"type":"Point"}
}
