{
  "type": "Feature",
  "properties": {
    "date:inception_lower": "2024-11-05",
    "date:inception_upper": "2024-11-05",
    "millsfield:wayfinding_detail": "G",
    "millsfield:wayfinding_kind": "ITB",
    "sfo:level": 2,
    "sfomuseum:placetype": "waypoint",
    "sfomuseum:post_security": 1,
    "wof:adjacencies": [
      1947330467,
      1947304867
    ],
    "wof:label": "T3 - International Terminal Post-Security Connector (ITB) (2024-11-05)",
    "wof:name": "T3 - International Terminal Post-Security Connector (ITB)",
    "wof:placetype": "venue",
    "wof:placetype_alt": [
      "waypoint"
    ]
  },
  "geometry": {"coordinates":[-122.38940949529083,37.61718354071702],"type":"Point"}
}
