{
  "type": "Feature",
  "properties": {
    "sfo:level": 2,
    "sfomuseum:placetype": "waypoint",
    "sfomuseum:post_security": 1,
    "wof:adjencies": [
      1796889541,
      1796903619
    ],
    "wof:name": "Boarding Area G End Pier",
    "wof:placetype": "venue",
    "wof:placetype_alt": "waypoint"
  },
  "geometry": {"coordinates":[-122.39299469438319,37.61851832981306],"type":"Point"}
}
