{
  "type": "Feature",
  "properties": {
    "sfo:level": 3,
    "sfomuseum:placetype": "waypoint",
    "wof:name": "Boarding Area G End Pier",
    "wof:placetype": "custom",
    "wof:placetype_alt": "waypoint"
  },
  "geometry": {"coordinates":[-122.39299469438319,37.61851832981306],"type":"Point"}
}
