{
  "type": "Feature",
  "properties": {
    "millsfield:wayfinding_detail": "ITB",
    "millsfield:wayfinding_kind": "ARR",
    "sfo:level": 1,
    "sfomuseum:placetype": "waypoint",
    "sfomuseum:post_security": 0,
    "wof:adjencies": [
      1797018155,
      1797018167
    ],
    "wof:name": "Internation Terminal Arrivals A Side",
    "wof:placetype": "venue",
    "wof:placetype_alt": "waypoint"
  },
  "geometry": {"coordinates":[-122.38956012462819,37.61496536156117],"type":"Point"}
}
