{
  "type": "Feature",
  "properties": {
    "sfo:level": 1,
    "sfomuseum:placetype": "waypoint",
    "sfomuseum:post_security": 0,
    "wof:name": "International Terminal Departures Door 2",
    "wof:placetype": "venue",
    "wof:placetype_alt": "waypoint"
  },
  "geometry": {"coordinates":[-122.38979938592807,37.61514221305148],"type":"Point"}
}
