{
  "type": "Feature",
  "properties": {
    "millsfield:wayfinding_detail": "PRE",
    "millsfield:wayfinding_kind": "ITB",
    "sfo:level": 1,
    "sfomuseum:placetype": "waypoint",
    "sfomuseum:post_security": 0,
    "wof:adjencies": [
      1796935613
    ],
    "wof:name": "International Terminal Main Hall Departures Door 2",
    "wof:placetype": "venue",
    "wof:placetype_alt": "waypoint"
  },
  "geometry": {"coordinates":[-122.38979938592807,37.61514221305148],"type":"Point"}
}
