{
  "type": "Feature",
  "properties": {
    "sfo:level": 2,
    "sfomuseum:placetype": "waypoint",
    "sfomuseum:post_security": 1,
    "wof:adjencies": [
      1796889487,
      1796889489,
      1796889491,
      1796889493,
      1796935573,
      1796935575,
      1796935603
    ],
    "wof:name": "Boarding Area D Center Court",
    "wof:placetype": "venue",
    "wof:placetype_alt": "waypoint"
  },
  "geometry": {"coordinates":[-122.38153636064618,37.617514823601844],"type":"Point"}
}
