{
  "type": "Feature",
  "properties": {
    "date:inception_lower": "2024-11-05",
    "date:inception_upper": "2024-11-05",
    "millsfield:wayfinding_detail": "D",
    "millsfield:wayfinding_kind": "T2",
    "sfo:level": 2,
    "sfomuseum:placetype": "waypoint",
    "sfomuseum:post_security": 1,
    "wof:adjacencies": [
      1947305355,
      1947305299,
      1947305297,
      1947304821,
      1947304933,
      1947305357
    ],
    "wof:label": "Boarding Area D End Pier (C) (2024-11-05)",
    "wof:name": "Boarding Area D End Pier (C)",
    "wof:placetype": "venue",
    "wof:placetype_alt": [
      "waypoint"
    ]
  },
  "geometry": {"coordinates":[-122.38100553733436,37.61707732930673],"type":"Point"}
}
