{
  "type": "Feature",
  "properties": {
    "date:inception_lower": "2024-06-17",
    "date:inception_upper": "2024-06-17",
    "millsfield:wayfinding_detail": "B",
    "millsfield:wayfinding_kind": "HMT1",
    "sfo:level": 2,
    "sfomuseum:placetype": "waypoint",
    "sfomuseum:post_security": 1,
    "wof:adjacencies": [
      1914666207
    ],
    "wof:label": "Gate B24 Waiting Area (2024-06-17)",
    "wof:name": "Gate B24 Waiting Area",
    "wof:placetype": "venue",
    "wof:placetype_alt": [
      "waypoint"
    ]
  },
  "geometry": {"coordinates":[-122.38617661162101,37.610593576389135],"type":"Point"}
}
