{
  "type": "Feature",
  "properties": {
    "date:inception_lower": "2024-11-05",
    "date:inception_upper": "2024-11-05",
    "sfo:level": 2,
    "sfomuseum:placetype": "waypoint",
    "wof:adjacencies": [
      1947305281
    ],
    "wof:name": "Gate G to Gate F Walkway G-Side",
    "wof:placetype": "venue"
  },
  "geometry": {"coordinates":[-122.38897517491237,37.61742634977798],"type":"Point"}
}
