{
  "type": "Feature",
  "properties": {
    "date:inception_lower": "2024-11-05",
    "date:inception_upper": "2024-11-05",
    "millsfield:wayfinding_detail": "C",
    "millsfield:wayfinding_kind": "T1",
    "sfo:level": 2,
    "sfomuseum:placetype": "waypoint",
    "sfomuseum:post_security": 1,
    "wof:adjacencies": [
      1947304839
    ],
    "wof:label": "Gate C10 Waiting Area (2024-11-05)",
    "wof:name": "Gate C10 Waiting Area",
    "wof:placetype": "venue",
    "wof:placetype_alt": [
      "waypoint"
    ]
  },
  "geometry": {"coordinates":[-122.38229944909034,37.61465650713998],"type":"Point"}
}
