{
  "type": "Feature",
  "properties": {
    "date:inception_lower": "2024-07-22",
    "date:inception_upper": "2024-07-22",
    "millsfield:wayfinding_kind": "PRK",
    "sfo:level": 0,
    "sfomuseum:placetype": "waypoint",
    "sfomuseum:post_security": 0,
    "wof:adjacencies": [
      1930431181
    ],
    "wof:name": "Long Term Parking 1",
    "wof:placetype": "venue",
    "wof:placetype_alt": [
      "waypoint"
    ]
  },
  "geometry": {"coordinates":[-122.40032,37.636211],"type":"Point"}
}
