{
  "type": "Feature",
  "properties": {
    "sfo:level": 3,
    "sfomuseum:placetype": "waypoint",
    "wof:adjencies": [
      1847571931,
      1847571933
    ],
    "wof:name": "Grand Hyatt Hotel Bar",
    "wof:placetype": "venue",
    "wof:placetype_alt": "waypoint"
  },
  "geometry": {"coordinates":[-122.39380627475495,37.61313609043349],"type":"Point"}
}
