{
  "type": "Feature",
  "properties": {
    "sfo:level": 2,
    "sfomuseum:placetype": "waypoint",
    "sfomuseum:post_security": 1,
    "wof:adjencies": [
      1796889529
    ],
    "wof:name": "Gates G9 - G10 Stairs Level 3",
    "wof:placetype": "venue",
    "wof:placetype_alt": "waypoint"
  },
  "geometry": {"coordinates":[-122.39260356632808,37.61846054221382],"type":"Point"}
}
