{
  "type": "Feature",
  "properties": {
    "date:inception_lower": "2024-06-17",
    "date:inception_upper": "2024-06-17",
    "millsfield:wayfinding_detail": "C",
    "millsfield:wayfinding_kind": "T1",
    "sfo:level": 2,
    "sfomuseum:placetype": "waypoint",
    "sfomuseum:post_security": 1,
    "wof:adjacenies": [
      1914666209
    ],
    "wof:adjencies": [
      1796889481
    ],
    "wof:label": "Gate C2 Waiting Area (2024-06-17)",
    "wof:name": "Gate C2 Waiting Area",
    "wof:placetype": "venue",
    "wof:placetype_alt": [
      "waypoint"
    ]
  },
  "geometry": {"coordinates":[-122.38359383410831,37.6151748603995],"type":"Point"}
}
