{
  "type": "Feature",
  "properties": {
    "date:inception_lower": "2024-11-05",
    "date:inception_upper": "2024-11-05",
    "millsfield:wayfinding_detail": "F",
    "millsfield:wayfinding_kind": "T3",
    "sfo:level": 2,
    "sfomuseum:placetype": "waypoint",
    "sfomuseum:post_security": 1,
    "wof:adjacencies": [
      1914666427,
      1914666249,
      1914666241,
      1914666259,
      1914666451,
      1914666439
    ],
    "wof:label": "Boarding Area F Mid Pier (2024-11-05)",
    "wof:name": "Boarding Area F Mid Pier",
    "wof:placetype": "venue",
    "wof:placetype_alt": [
      "waypoint"
    ]
  },
  "geometry": {"coordinates":[-122.38745603971715,37.61998552310207],"type":"Point"}
}
