{
  "type": "Feature",
  "properties": {
    "date:inception_lower": "2024-07-22",
    "date:inception_upper": "2024-07-22",
    "millsfield:wayfinding_detail": "PRK",
    "millsfield:wayfinding_kind": "ATR",
    "sfo:level": 3,
    "sfomuseum:placetype": "waypoint",
    "sfomuseum:post_security": 0,
    "wof:adjacencies": [
      1914666623,
      1914666295
    ],
    "wof:name": "AirTrain Garage G / BART Blue Line",
    "wof:placetype": "venue",
    "wof:placetype_alt": [
      "waypoint"
    ]
  },
  "geometry": {"coordinates":[-122.39254277183558,37.61606385174821],"type":"Point"}
}
