{
  "type": "Feature",
  "properties": {
    "date:inception_lower": "2021-01-01",
    "date:inception_upper": "2021-12-31",
    "sfo:level": 2,
    "sfomuseum:placetype": "waypoint",
    "sfomuseum:post_security": 1,
    "wof:name": "Harvey Milk Terminal 1 to International Terminal A Connector (Harvey Milk Terminal)",
    "wof:placetype": "venue"
  },
  "geometry": {"coordinates":[-122.387528,37.614392],"type":"Point"}
}
