{
  "type": "Feature",
  "properties": {
    "date:inception_lower": "2024-06-17",
    "date:inception_upper": "2024-06-17",
    "millsfield:wayfinding_detail": "DEP",
    "millsfield:wayfinding_kind": "HMT1",
    "sfo:level": 1,
    "sfomuseum:placetype": "waypoint",
    "sfomuseum:post_security": 0,
    "wof:adjacenies": [
      1914666393,
      1914666809
    ],
    "wof:adjencies": [
      1796889629,
      1797018159
    ],
    "wof:label": "Harvey Milk Terminal 1 Baggage Claim - Departures Stairs Level 2 (2024-06-17)",
    "wof:name": "Harvey Milk Terminal 1 Baggage Claim - Departures Stairs Level 2",
    "wof:placetype": "venue",
    "wof:placetype_alt": [
      "waypoint"
    ]
  },
  "geometry": {"coordinates":[-122.38704175598171,37.614737746229046],"type":"Point"}
}
