{
  "type": "Feature",
  "properties": {
    "date:inception_lower": "2024-11-05",
    "date:inception_upper": "2024-11-05",
    "millsfield:wayfinding_detail": "A",
    "millsfield:wayfinding_kind": "ITB",
    "sfo:level": 2,
    "sfomuseum:placetype": "waypoint",
    "sfomuseum:post_security": 1,
    "wof:adjacencies": [
      1947304893,
      1947304877,
      1947305381
    ],
    "wof:label": "Gate A9 - A10 Waiting Area Level 3 (2024-11-05)",
    "wof:name": "Gate A9 - A10 Waiting Area Level 3",
    "wof:placetype": "venue",
    "wof:placetype_alt": [
      "waypoint"
    ]
  },
  "geometry": {"coordinates":[-122.38978420756682,37.61253257346998],"type":"Point"}
}
