{
  "type": "Feature",
  "properties": {
    "date:inception_lower": "2024-06-17",
    "date:inception_upper": "2024-06-17",
    "millsfield:wayfinding_detail": "DEP",
    "millsfield:wayfinding_kind": "SFO",
    "sfo:level": 2,
    "sfomuseum:placetype": "waypoint",
    "sfomuseum:post_security": 0,
    "wof:adjacencies": [
      1914666367,
      1914666375
    ],
    "wof:label": "T3 - International Terminal Pre-Security Connector (2024-06-17)",
    "wof:name": "T3 - International Terminal Pre-Security Connector",
    "wof:placetype": "venue",
    "wof:placetype_alt": [
      "waypoint"
    ]
  },
  "geometry": {"coordinates":[-122.3885189456314,37.61687669403899],"type":"Point"}
}
