{
  "type": "Feature",
  "properties": {
    "date:inception_lower": "2024-07-22",
    "date:inception_upper": "2024-07-22",
    "millsfield:wayfinding_detail": "PRK",
    "millsfield:wayfinding_kind": "ATR",
    "sfo:level": 0,
    "sfomuseum:placetype": "waypoint",
    "sfomuseum:post_security": 0,
    "wof:adjencies": [
      1796982279
    ],
    "wof:name": "AirTrain Long-Term Parking Blue Line (Outbound)",
    "wof:placetype": "venue",
    "wof:placetype_alt": [
      "waypoint"
    ]
  },
  "geometry": {"coordinates":[-122.40020209788976,37.63495659688203],"type":"Point"}
}
