{
  "type": "Feature",
  "properties": {
    "date:inception_lower": "2024-06-17",
    "date:inception_upper": "2024-06-17",
    "millsfield:wayfinding_detail": "E",
    "millsfield:wayfinding_kind": "T3",
    "sfo:level": 2,
    "sfomuseum:placetype": "waypoint",
    "sfomuseum:post_security": 1,
    "wof:adjencies": [
      1796935363,
      1796935369,
      1796935361,
      1796889497,
      1796889499,
      1796935367
    ],
    "wof:label": "Boarding Area E Mid Pier (2024-06-17)",
    "wof:name": "Boarding Area E Mid Pier",
    "wof:placetype": "venue",
    "wof:placetype_alt": [
      "waypoint"
    ]
  },
  "geometry": {"coordinates":[-122.38457853417695,37.618744924875394],"type":"Point"}
}
