{
  "type": "Feature",
  "properties": {
    "date:inception_lower": "2024-11-05",
    "date:inception_upper": "2024-11-05",
    "millsfield:wayfinding_detail": "ARR",
    "millsfield:wayfinding_kind": "ITB",
    "sfo:level": 3,
    "sfomuseum:placetype": "waypoint",
    "sfomuseum:post_security": 0,
    "wof:adjacencies": [
      1947305399,
      1947305407
    ],
    "wof:label": "Internation Terminal Arrivals A Side (2024-11-05)",
    "wof:name": "Internation Terminal Arrivals A Side",
    "wof:placetype": "venue",
    "wof:placetype_alt": [
      "waypoint"
    ]
  },
  "geometry": {"coordinates":[-122.38956012462819,37.61496536156117],"type":"Point"}
}
