{
  "type": "Feature",
  "properties": {
    "date:inception_lower": "2024-11-05",
    "date:inception_upper": "2024-11-05",
    "millsfield:wayfinding_detail": "HMT1",
    "millsfield:wayfinding_kind": "ATR",
    "sfo:level": 6,
    "sfomuseum:placetype": "waypoint",
    "wof:adjacencies": [
      1947305443,
      1947304911
    ],
    "wof:label": "AirTrain Harvey Milk Terminal 1 Red Line (2024-11-05)",
    "wof:name": "AirTrain Harvey Milk Terminal 1 Red Line",
    "wof:placetype": "custom",
    "wof:placetype_alt": [
      "waypoint"
    ]
  },
  "geometry": {"coordinates":[-122.38556950061454,37.61526896102093],"type":"Point"}
}
