{
  "type": "Feature",
  "properties": {
    "date:inception_lower": "2024-06-17",
    "date:inception_upper": "2024-06-17",
    "millsfield:wayfinding_kind": "SFO",
    "sfo:level": 2,
    "sfomuseum:placetype": "waypoint",
    "sfomuseum:post_security": 1,
    "wof:adjacenies": [
      1914666317,
      1914666315
    ],
    "wof:adjencies": [
      1796889579,
      1796889575
    ],
    "wof:label": "T2 - T3 Post-Security Connector (2024-06-17)",
    "wof:name": "T2 - T3 Post-Security Connector",
    "wof:placetype": "venue",
    "wof:placetype_alt": [
      "waypoint"
    ]
  },
  "geometry": {"coordinates":[-122.38410326294378,37.61776797845168],"type":"Point"}
}
