{
  "type": "Feature",
  "properties": {
    "sfo:level": 2,
    "sfomuseum:placetype": "waypoint",
    "wof:adjencies": [
      1796889509,
      1796889513,
      1796889517
    ],
    "wof:name": "Boarding Area F Mid Pier",
    "wof:placetype": "custom",
    "wof:placetype_alt": "waypoint"
  },
  "geometry": {"coordinates":[-122.38745603971715,37.61998552310207],"type":"Point"}
}
