{
  "type": "Feature",
  "properties": {
    "sfo:level": 2,
    "sfomuseum:placetype": "waypoint",
    "sfomuseum:post_security": 1,
    "wof:adjencies": [
      1796935385,
      1796889509,
      1796889513,
      1796889517,
      1796935399,
      1796935397
    ],
    "wof:name": "Boarding Area F Mid Pier",
    "wof:placetype": "venue",
    "wof:placetype_alt": "waypoint"
  },
  "geometry": {"coordinates":[-122.38745603971715,37.61998552310207],"type":"Point"}
}
