{
  "type": "Feature",
  "properties": {
    "date:inception_lower": "2024-06-17",
    "date:inception_upper": "2024-06-17",
    "millsfield:wayfinding_detail": "G",
    "millsfield:wayfinding_kind": "ITB",
    "sfo:level": 3,
    "sfomuseum:placetype": "waypoint",
    "sfomuseum:post_security": 1,
    "wof:adjencies": [
      1797041269,
      1796889527,
      1796889541,
      1796903593,
      1797018085
    ],
    "wof:label": "Boarding Area G Start Pier (2024-06-17)",
    "wof:name": "Boarding Area G Start Pier",
    "wof:placetype": "venue",
    "wof:placetype_alt": [
      "waypoint"
    ]
  },
  "geometry": {"coordinates":[-122.38962014981846,37.61705113652405],"type":"Point"}
}
