{
  "type": "Feature",
  "properties": {
    "date:inception_lower": "2024-06-17",
    "date:inception_upper": "2024-06-17",
    "millsfield:wayfinding_detail": "ITB",
    "millsfield:wayfinding_kind": "ATR",
    "sfo:level": 3,
    "sfomuseum:placetype": "waypoint",
    "sfomuseum:post_security": 0,
    "wof:adjacencies": [
      1914666319,
      1914666557
    ],
    "wof:label": "AirTrain International Terminal A Red Line (2024-06-17)",
    "wof:name": "AirTrain International Terminal A Red Line",
    "wof:placetype": "venue",
    "wof:placetype_alt": [
      "waypoint"
    ]
  },
  "geometry": {"coordinates":[-122.38877238550087,37.61465481561797],"type":"Point"}
}
