{
  "type": "Feature",
  "properties": {
    "date:inception_lower": "2024-06-17",
    "date:inception_upper": "2024-06-17",
    "millsfield:wayfinding_detail": "ITB",
    "millsfield:wayfinding_kind": "ATR",
    "sfo:level": 3,
    "sfomuseum:placetype": "waypoint",
    "sfomuseum:post_security": 0,
    "wof:adjencies": [
      1796982275,
      1796889543
    ],
    "wof:label": "Air Train International Terminal G Blue Line (2024-06-17)",
    "wof:name": "Air Train International Terminal G Blue Line",
    "wof:placetype": "venue",
    "wof:placetype_alt": [
      "waypoint"
    ]
  },
  "geometry": {"coordinates":[-122.3895404706656,37.616696820978746],"type":"Point"}
}
