{
  "type": "Feature",
  "properties": {
    "millsfield:wayfinding_detail": "DEP",
    "millsfield:wayfinding_kind": "T3",
    "sfo:level": 1,
    "sfomuseum:placetype": "waypoint",
    "sfomuseum:post_security": 0,
    "wof:adjencies": [
      1797018127,
      1796935373
    ],
    "wof:name": "Terminal 3 Baggage Claim - Boarding Area E Meet and Greet Stairs Level 2",
    "wof:placetype": "venue",
    "wof:placetype_alt": [
      "waypoint"
    ]
  },
  "geometry": {"coordinates":[-122.38503954346581,37.61798361137215],"type":"Point"}
}
