{
  "type": "Feature",
  "properties": {
    "millsfield:wayfinding_detail": "T3",
    "millsfield:wayfinding_kind": "PRE",
    "sfo:level": 2,
    "sfomuseum:placetype": "waypoint",
    "sfomuseum:post_security": 0,
    "wof:name": "Terminal 3 Baggage Claim - Boarding Area E Meet and Greet Stairs Level 3",
    "wof:placetype": "venue",
    "wof:placetype_alt": "waypoint"
  },
  "geometry": {"coordinates":[-122.38503954346581,37.61798361137215],"type":"Point"}
}
