{
  "type": "Feature",
  "properties": {
    "millsfield:wayfinding_detail": "PRE",
    "millsfield:wayfinding_kind": "ITB",
    "sfo:level": 1,
    "sfomuseum:placetype": "waypoint",
    "sfomuseum:post_security": 0,
    "wof:adjencies": [
      1796889639
    ],
    "wof:name": "International Terminal Main Hall G Side Arrivals Stairs",
    "wof:placetype": "venue",
    "wof:placetype_alt": "waypoint"
  },
  "geometry": {"coordinates":[-122.39002290263893,37.61632322351207],"type":"Point"}
}
