{
  "type": "Feature",
  "properties": {
    "date:inception_lower": "2024-07-22",
    "date:inception_upper": "2024-07-22",
    "millsfield:wayfinding_detail": "PRK",
    "millsfield:wayfinding_kind": "ATR",
    "sfo:level": 0,
    "sfomuseum:placetype": "waypoint",
    "sfomuseum:post_security": 0,
    "wof:adjacencies": [
      1930431167,
      1930431169,
      1930431139
    ],
    "wof:name": "AirTrain Long-Term Parking Station",
    "wof:placetype": "venue",
    "wof:placetype_alt": [
      "waypoint"
    ]
  },
  "geometry": {"coordinates":[-122.40029129399466,37.634972022421096],"type":"Point"}
}
