{
  "type": "Feature",
  "properties": {
    "date:inception_lower": "2024-06-17",
    "date:inception_upper": "2024-06-17",
    "millsfield:wayfinding_detail": "A",
    "millsfield:wayfinding_kind": "ITB",
    "sfo:level": 2,
    "sfomuseum:placetype": "waypoint",
    "sfomuseum:post_security": 1,
    "wof:adjacenies": [
      1914666559,
      1914666735
    ],
    "wof:adjencies": [
      1796935459,
      1797018099
    ],
    "wof:label": "Gate A2 Waiting Area (2024-06-17)",
    "wof:name": "Gate A2 Waiting Area",
    "wof:placetype": "venue",
    "wof:placetype_alt": [
      "waypoint"
    ]
  },
  "geometry": {"coordinates":[-122.38876785929067,37.61342964122441],"type":"Point"}
}
