{
  "type": "Feature",
  "properties": {
    "sfomuseum:placetype": "waypoint",
    "wof:adjencies": [
      1796903641
    ],
    "wof:name": "Long Term Parking 1",
    "wof:placetype": "venue",
    "wof:placetype_alt": "waypoint"
  },
  "geometry": {"coordinates":[-122.40050241320299,37.63661875135711],"type":"Point"}
}
