{
  "type": "Feature",
  "properties": {
    "sfo:level": 1,
    "sfomuseum:placetype": "waypoint",
    "sfomuseum:post_security": 0,
    "wof:name": "International Terminal Departures Door 3",
    "wof:placetype": "venue",
    "wof:placetype_alt": "waypoint"
  },
  "geometry": {"coordinates":[-122.39001585082727,37.615721672935486],"type":"Point"}
}
