{
  "type": "Feature",
  "properties": {
    "sfomuseum:placetype": "waypoint",
    "sfomuseum:post_security": 0,
    "wof:name": "AirTrain Terminal 1 Red Line",
    "wof:placetype": "venue",
    "wof:placetype_alt": "waypoint"
  },
  "geometry": {"coordinates":[-122.38565910706276,37.61522060227708],"type":"Point"}
}
