{
  "type": "Feature",
  "properties": {
    "date:inception_lower": "2024-06-17",
    "date:inception_upper": "2024-06-17",
    "millsfield:wayfinding_detail": "D",
    "millsfield:wayfinding_kind": "T2",
    "sfo:level": 2,
    "sfomuseum:placetype": "waypoint",
    "sfomuseum:post_security": 1,
    "wof:adjencies": [
      1796889491
    ],
    "wof:label": "Gate D8 Waiting Area (2024-06-17)",
    "wof:name": "Gate D8 Waiting Area",
    "wof:placetype": "venue",
    "wof:placetype_alt": [
      "waypoint"
    ]
  },
  "geometry": {"coordinates":[-122.38096972216312,37.617303412575204],"type":"Point"}
}
