{
  "type": "Feature",
  "properties": {
    "date:inception_lower": "2024-06-17",
    "date:inception_upper": "2024-06-17",
    "millsfield:wayfinding_detail": "A",
    "millsfield:wayfinding_kind": "ITB",
    "sfo:level": 2,
    "sfomuseum:placetype": "waypoint",
    "sfomuseum:post_security": 1,
    "wof:adjacencies": [
      1914666765,
      1914666265
    ],
    "wof:label": "Gate A3 - A5 Waiting Area Level 3 (2024-06-17)",
    "wof:name": "Gate A3 - A5 Waiting Area Level 3",
    "wof:placetype": "venue",
    "wof:placetype_alt": [
      "waypoint"
    ]
  },
  "geometry": {"coordinates":[-122.38909723211361,37.613560288031955],"type":"Point"}
}
