{
  "type": "Feature",
  "properties": {
    "date:inception_lower": "2024-11-05",
    "date:inception_upper": "2024-11-05",
    "sfo:level": 2,
    "sfomuseum:placetype": "waypoint",
    "sfomuseum:post_security": 1,
    "wof:adjacencies": [
      1914666227,
      1914666851
    ],
    "wof:label": "Alley Gallery Entrance (2024-11-05)",
    "wof:name": "Alley Gallery Entrance",
    "wof:placetype": "venue",
    "wof:placetype_alt": [
      "waypoint"
    ]
  },
  "geometry": {"coordinates":[-122.385187,37.614004],"type":"Point"}
}
