{
  "type": "Feature",
  "properties": {
    "date:inception_lower": "2024-11-05",
    "date:inception_upper": "2024-11-05",
    "sfo:level": 2,
    "sfomuseum:placetype": "waypoint",
    "wof:adjacencies": [
      1947304835,
      1947330499
    ],
    "wof:name": "Gate E to Gate F Walkway F-Side",
    "wof:placetype": "venue"
  },
  "geometry": {"coordinates":[-122.3869790955598,37.61969724221758],"type":"Point"}
}
