{
  "type": "Feature",
  "properties": {
    "sfo:level": 2,
    "sfomuseum:placetype": "waypoint",
    "sfomuseum:post_security": 1,
    "wof:adjencies": [
      1796889567,
      1796935553,
      1796935555,
      1796935559,
      1796935557,
      1796935551
    ],
    "wof:name": "Boarding Area C End Pier",
    "wof:placetype": "venue",
    "wof:placetype_alt": "waypoint"
  },
  "geometry": {"coordinates":[-122.38246357718941,37.61482921799332],"type":"Point"}
}
