{
  "type": "Feature",
  "properties": {
    "sfo:level": 3,
    "sfomuseum:placetype": "waypoint",
    "wof:adjencies": [
      1796889567
    ],
    "wof:name": "Boarding Area C End Pier",
    "wof:placetype": "custom",
    "wof:placetype_alt": "waypoint"
  },
  "geometry": {"coordinates":[-122.38246357718941,37.61482921799332],"type":"Point"}
}
