{
  "type": "Feature",
  "properties": {
    "millsfield:wayfinding_detail": "ATR",
    "millsfield:wayfinding_kind": "T2",
    "sfo:level": 1,
    "sfomuseum:placetype": "waypoint",
    "sfomuseum:post_security": 0,
    "wof:adjencies": [
      1797018115,
      1796935569,
      1796935565
    ],
    "wof:name": "AirTrain Terminal 2 Stairs West Level 3",
    "wof:placetype": "venue",
    "wof:placetype_alt": "waypoint"
  },
  "geometry": {"coordinates":[-122.38385750513046,37.61701156876989],"type":"Point"}
}
