{
  "type": "Feature",
  "properties": {
    "sfomuseum:placetype": "waypoint",
    "wof:name": "AirTrain Terminal 2 Stairs West",
    "wof:placetype": "venue",
    "wof:placetype_alt": "waypoint"
  },
  "geometry": {"coordinates":[-122.38385750513046,37.61701156876989],"type":"Point"}
}
