{
  "type": "Feature",
  "properties": {
    "sfo:level": 1,
    "sfomuseum:placetype": "waypoint",
    "sfomuseum:post_security": 0,
    "wof:adjencies": [
      1796935565,
      1796889597,
      1796889599,
      1796935571,
      1796935569
    ],
    "wof:name": "AirTrain Terminal 2 Stairs West",
    "wof:placetype": "venue",
    "wof:placetype_alt": "waypoint"
  },
  "geometry": {"coordinates":[-122.38385750513046,37.61701156876989],"type":"Point"}
}
