{
  "type": "Feature",
  "properties": {
    "date:inception_lower": "2024-06-17",
    "date:inception_upper": "2024-06-17",
    "millsfield:wayfinding_detail": "G",
    "millsfield:wayfinding_kind": "ITB",
    "sfo:level": 2,
    "sfomuseum:placetype": "waypoint",
    "sfomuseum:post_security": 1,
    "wof:adjacencies": [
      1914666277,
      1914666727
    ],
    "wof:label": "Gate G3 - G4 Waiting Area Level 3 (2024-06-17)",
    "wof:name": "Gate G3 - G4 Waiting Area Level 3",
    "wof:placetype": "venue",
    "wof:placetype_alt": [
      "waypoint"
    ]
  },
  "geometry": {"coordinates":[-122.39137219975575,37.61766919078866],"type":"Point"}
}
