{
  "type": "Feature",
  "properties": {
    "date:inception_lower": "2024-06-17",
    "date:inception_upper": "2024-06-17",
    "millsfield:wayfinding_detail": "E",
    "millsfield:wayfinding_kind": "T3",
    "sfo:level": 2,
    "sfomuseum:placetype": "waypoint",
    "sfomuseum:post_security": 1,
    "wof:adjencies": [
      1796889499
    ],
    "wof:label": "Gate E12 Waiting Area (2024-06-17)",
    "wof:name": "Gate E12 Waiting Area",
    "wof:placetype": "venue",
    "wof:placetype_alt": [
      "waypoint"
    ]
  },
  "geometry": {"coordinates":[-122.38424130850507,37.619430396745905],"type":"Point"}
}
