{
  "type": "Feature",
  "properties": {
    "sfomuseum:placetype": "waypoint",
    "wof:name": "Gate B24 Waiting Area",
    "wof:placetype": "venue",
    "wof:placetype_alt": "waypoint"
  },
  "geometry": {"coordinates":[-122.38617661162101,37.610593576389135],"type":"Point"}
}
