{
  "type": "Feature",
  "properties": {
    "millsfield:wayfinding_detail": "B",
    "millsfield:wayfinding_kind": "HMT1",
    "sfo:level": 2,
    "sfomuseum:placetype": "waypoint",
    "sfomuseum:post_security": 1,
    "wof:adjencies": [
      1796889469
    ],
    "wof:name": "Gate B24 Waiting Area",
    "wof:placetype": "venue",
    "wof:placetype_alt": "waypoint"
  },
  "geometry": {"coordinates":[-122.38617661162101,37.610593576389135],"type":"Point"}
}
