{
  "type": "Feature",
  "properties": {
    "date:inception_lower": "2024-06-17",
    "date:inception_upper": "2024-06-17",
    "millsfield:wayfinding_detail": "GHH",
    "millsfield:wayfinding_kind": "ATR",
    "sfo:level": 5,
    "sfomuseum:placetype": "waypoint",
    "sfomuseum:post_security": 0,
    "wof:adjacenies": [
      1914666299,
      1914666289,
      1914666477
    ],
    "wof:adjencies": [
      1796903599,
      1796889551,
      1796903625
    ],
    "wof:label": "AirTrain Grand Hyatt Hotel Station (2024-06-17)",
    "wof:name": "AirTrain Grand Hyatt Hotel Station",
    "wof:placetype": "venue",
    "wof:placetype_alt": [
      "waypoint"
    ]
  },
  "geometry": {"coordinates":[-122.39332890371237,37.613435201247555],"type":"Point"}
}
