{
  "type": "Feature",
  "properties": {
    "date:inception_lower": "2024-06-17",
    "date:inception_upper": "2024-06-17",
    "millsfield:wayfinding_detail": "A",
    "millsfield:wayfinding_kind": "ITB",
    "sfo:level": 2,
    "sfomuseum:placetype": "waypoint",
    "sfomuseum:post_security": 1,
    "wof:adjacencies": [
      1914666517,
      1914666771,
      1914666565
    ],
    "wof:label": "Gate A9 - A10 Stairs Level 2 (2024-06-17)",
    "wof:name": "Gate A9 - A10 Stairs Level 2",
    "wof:placetype": "venue",
    "wof:placetype_alt": [
      "waypoint"
    ]
  },
  "geometry": {"coordinates":[-122.38975666121218,37.61245192186209],"type":"Point"}
}
