{
  "type": "Feature",
  "properties": {
    "date:inception_lower": "2024-06-17",
    "date:inception_upper": "2024-06-17",
    "millsfield:wayfinding_detail": "E",
    "millsfield:wayfinding_kind": "T3",
    "sfo:level": 2,
    "sfomuseum:placetype": "waypoint",
    "sfomuseum:post_security": 1,
    "wof:adjencies": [
      1796889581,
      1796889497
    ],
    "wof:label": "Gate E3 Waiting Area (2024-06-17)",
    "wof:name": "Gate E3 Waiting Area",
    "wof:placetype": "venue",
    "wof:placetype_alt": [
      "waypoint"
    ]
  },
  "geometry": {"coordinates":[-122.38562087924608,37.61857452948481],"type":"Point"}
}
