{
  "type": "Feature",
  "properties": {
    "date:inception_lower": "2024-11-05",
    "date:inception_upper": "2024-11-05",
    "millsfield:wayfinding_detail": "F",
    "millsfield:wayfinding_kind": "T3",
    "sfo:level": 2,
    "sfomuseum:placetype": "waypoint",
    "sfomuseum:post_security": 1,
    "wof:adjacencies": [
      1947304857
    ],
    "wof:label": "Gate F21 Waiting Area (2024-11-05)",
    "wof:name": "Gate F21 Waiting Area",
    "wof:placetype": "venue",
    "wof:placetype_alt": [
      "waypoint"
    ]
  },
  "geometry": {"coordinates":[-122.39013574658719,37.62115447860882],"type":"Point"}
}
