{
  "type": "Feature",
  "properties": {
    "millsfield:wayfinding_kind": "GHH",
    "sfo:level": 0,
    "sfomuseum:placetype": "waypoint",
    "sfomuseum:post_security": 0,
    "wof:adjencies": [
      1847571947,
      1796942175,
      1796942181
    ],
    "wof:name": "Grand Hyatt Hotel Level 1",
    "wof:placetype": "venue",
    "wof:placetype_alt": "waypoint"
  },
  "geometry": {"coordinates":[-122.39393193080298,37.61291892129142],"type":"Point"}
}
