{
  "type": "Feature",
  "properties": {
    "sfo:level": 3,
    "sfomuseum:placetype": "waypoint",
    "wof:name": "Boarding Area D Start Pier",
    "wof:placetype": "custom",
    "wof:placetype_alt": "waypoint"
  },
  "geometry": {"coordinates":[-122.38294148881829,37.61716068743153],"type":"Point"}
}
