{
  "type": "Feature",
  "properties": {
    "sfo:level": 2,
    "sfomuseum:placetype": "waypoint",
    "sfomuseum:post_security": 1,
    "wof:adjencies": [
      1796889485,
      1796889487,
      1796889571,
      1796889611
    ],
    "wof:name": "Boarding Area D Start Pier",
    "wof:placetype": "venue",
    "wof:placetype_alt": "waypoint"
  },
  "geometry": {"coordinates":[-122.38294148881829,37.61716068743153],"type":"Point"}
}
