{
  "type": "Feature",
  "properties": {
    "millsfield:wayfinding_detail": "B",
    "millsfield:wayfinding_kind": "HMT1",
    "sfo:level": 2,
    "sfomuseum:placetype": "waypoint",
    "sfomuseum:post_security": 1,
    "wof:adjencies": [
      1796889475
    ],
    "wof:name": "Gate B8 Waiting Area",
    "wof:placetype": "venue",
    "wof:placetype_alt": "waypoint"
  },
  "geometry": {"coordinates":[-122.38427098923346,37.61307597913772],"type":"Point"}
}
