{
  "type": "Feature",
  "properties": {
    "date:inception_lower": "2024-06-17",
    "date:inception_upper": "2024-06-17",
    "millsfield:wayfinding_detail": "B",
    "millsfield:wayfinding_kind": "HMT1",
    "sfo:level": 2,
    "sfomuseum:placetype": "waypoint",
    "sfomuseum:post_security": 1,
    "wof:adjacencies": [
      1914666819,
      1914666569,
      1914666575,
      1914666395,
      1914666227
    ],
    "wof:label": "Boarding Area B ITB (2024-06-17)",
    "wof:name": "Boarding Area B ITB",
    "wof:placetype": "venue",
    "wof:placetype_alt": [
      "waypoint"
    ]
  },
  "geometry": {"coordinates":[-122.386059457822,37.61405680174487],"type":"Point"}
}
