{
  "type": "Feature",
  "properties": {
    "sfo:level": 1,
    "sfomuseum:placetype": "waypoint",
    "sfomuseum:post_security": 0,
    "wof:adjencies": [
      1796889637
    ],
    "wof:name": "ITB A Arrivals Stairs",
    "wof:placetype": "venue",
    "wof:placetype_alt": "waypoint"
  },
  "geometry": {"coordinates":[-122.38939076725296,37.61469759030689],"type":"Point"}
}
