{
  "type": "Feature",
  "properties": {
    "sfomuseum:placetype": "waypoint",
    "wof:name": "ITB A Arrivals Stairs",
    "wof:placetype": "custom",
    "wof:placetype_alt": "waypoint"
  },
  "geometry": {"coordinates":[-122.38939076725296,37.61469759030689],"type":"Point"}
}
