{
  "type": "Feature",
  "properties": {
    "millsfield:wayfinding_detail": "T2",
    "millsfield:wayfinding_kind": "PRE",
    "sfo:level": 2,
    "sfomuseum:placetype": "waypoint",
    "wof:name": "AirTrain Terminal 2 Stairs Level 2",
    "wof:placetype": "venue",
    "wof:placetype_alt": "waypoint"
  },
  "geometry": {"coordinates":[-122.38348844206891,37.616969092836385],"type":"Point"}
}
