{
  "type": "Feature",
  "properties": {
    "millsfield:wayfinding_detail": "HMT1",
    "millsfield:wayfinding_kind": "PRE",
    "sfo:level": 2,
    "sfomuseum:placetype": "waypoint",
    "sfomuseum:post_security": 0,
    "wof:adjencies": [
      1796889629,
      1797018159
    ],
    "wof:name": "Harvey Milk Terminal 1 Baggage Claim - Departures Stairs Level 2",
    "wof:placetype": "venue",
    "wof:placetype_alt": "waypoint"
  },
  "geometry": {"coordinates":[-122.38704175598171,37.614737746229046],"type":"Point"}
}
