{
  "type": "Feature",
  "properties": {
    "sfomuseum:placetype": "waypoint",
    "wof:name": "Gate B26 Waiting Area",
    "wof:placetype": "venue",
    "wof:placetype_alt": "waypoint"
  },
  "geometry": {"coordinates":[-122.3863054508705,37.61081230348708],"type":"Point"}
}
