{
  "type": "Feature",
  "properties": {
    "millsfield:wayfinding_detail": "HMT1",
    "millsfield:wayfinding_kind": "ATR",
    "sfo:level": 6,
    "sfomuseum:placetype": "waypoint",
    "wof:adjencies": [
      1863412741,
      1863412745,
      1863412743
    ],
    "wof:name": "AirTrain Harvey Milk Terminal 1 Station",
    "wof:placetype": "custom",
    "wof:placetype_alt": [
      "waypoint"
    ]
  },
  "geometry": {"coordinates":[-122.38567767064657,37.615192425676256],"type":"Point"}
}
