{
  "type": "Feature",
  "properties": {
    "millsfield:wayfinding_detail": "A",
    "millsfield:wayfinding_kind": "ITA",
    "sfo:level": 2,
    "sfomuseum:placetype": "waypoint",
    "sfomuseum:post_security": 1,
    "wof:adjencies": [
      1797041267,
      1796889533,
      1797018091
    ],
    "wof:name": "Gate A6 - A8 Stairs Level 3",
    "wof:placetype": "venue",
    "wof:placetype_alt": "waypoint"
  },
  "geometry": {"coordinates":[-122.38949063623448,37.61244668690732],"type":"Point"}
}
