{
  "type": "Feature",
  "properties": {
    "millsfield:wayfinding_detail": "ITB",
    "millsfield:wayfinding_kind": "A",
    "sfo:level": 3,
    "sfomuseum:placetype": "waypoint",
    "wof:name": "Gate A6 - A8 Stairs Level 3",
    "wof:placetype": "venue",
    "wof:placetype_alt": "waypoint"
  },
  "geometry": {"coordinates":[-122.38949063623448,37.61244668690732],"type":"Point"}
}
