{
  "type": "Feature",
  "properties": {
    "date:inception_lower": "2024-11-05",
    "date:inception_upper": "2024-11-05",
    "millsfield:wayfinding_detail": "DEP",
    "millsfield:wayfinding_kind": "SFO",
    "sfo:level": 2,
    "sfomuseum:placetype": "waypoint",
    "sfomuseum:post_security": 0,
    "wof:adjacencies": [
      1914666351,
      1914666355
    ],
    "wof:label": "T2 - T3 Pre-Security Connector (2024-11-05)",
    "wof:name": "T2 - T3 Pre-Security Connector",
    "wof:placetype": "venue",
    "wof:placetype_alt": [
      "waypoint"
    ]
  },
  "geometry": {"coordinates":[-122.38457390391878,37.61764427006395],"type":"Point"}
}
