{
  "type": "Feature",
  "properties": {
    "date:inception_lower": "2024-11-05",
    "date:inception_upper": "2024-11-05",
    "millsfield:wayfinding_detail": "T3",
    "millsfield:wayfinding_kind": "ATR",
    "sfo:level": 4,
    "sfomuseum:placetype": "waypoint",
    "sfomuseum:post_security": -1,
    "wof:adjacencies": [
      1947305231,
      1947305135
    ],
    "wof:label": "AirTrain Terminal 3 Red Line (2024-11-05)",
    "wof:name": "AirTrain Terminal 3 Red Line",
    "wof:placetype": "venue",
    "wof:placetype_alt": [
      "waypoint"
    ]
  },
  "geometry": {"coordinates":[-122.38657478595175,37.617469389770456],"type":"Point"}
}
