{
  "type": "Feature",
  "properties": {
    "sfo:level": 2,
    "sfomuseum:placetype": "waypoint",
    "wof:adjencies": [
      1796889611,
      1796889549,
      1796889597,
      1796889601,
      1796903627
    ],
    "wof:name": "Terminal 2 Pre Security",
    "wof:placetype": "custom",
    "wof:placetype_alt": "waypoint"
  },
  "geometry": {"coordinates":[-122.3836902262547,37.616990485905845],"type":"Point"}
}
