{
  "type": "Feature",
  "properties": {
    "millsfield:wayfinding_detail": "PRE",
    "millsfield:wayfinding_kind": "T2",
    "sfo:level": 1,
    "sfomuseum:placetype": "waypoint",
    "sfomuseum:post_security": 0,
    "wof:adjencies": [
      1797018113,
      1796889597,
      1796889601,
      1796889611,
      1796935571,
      1797018115,
      1797018109
    ],
    "wof:name": "Terminal 2 Main Hall",
    "wof:placetype": "venue",
    "wof:placetype_alt": "waypoint"
  },
  "geometry": {"coordinates":[-122.3836902262547,37.616990485905845],"type":"Point"}
}
