{
  "type": "Feature",
  "properties": {
    "millsfield:wayfinding_detail": "T3",
    "millsfield:wayfinding_kind": "PRE",
    "sfo:level": 2,
    "sfomuseum:placetype": "waypoint",
    "sfomuseum:post_security": 0,
    "wof:adjencies": [
      1796889589,
      1796889525,
      1796889587
    ],
    "wof:name": "AirTrain Terminal 3 Stairs Level 2",
    "wof:placetype": "venue",
    "wof:placetype_alt": "waypoint"
  },
  "geometry": {"coordinates":[-122.38686072642571,37.61824393739529],"type":"Point"}
}
